{
  "ALLImport.tpl": {
    "module": "builder",
    "moduleScope": "main",
    "hostKey": "localhost",
    "filePath": "templates/java",
    "fileName": "ALLImport.tpl",
    "description": "Creates the general import list from field javaImport generated by the java generator. ",
    "expose": "WEB",
    "cached": "true"
  },
  "ALLInstanceVars.tpl": {
    "module": "builder",
    "moduleScope": "main",
    "hostKey": "localhost",
    "filePath": "templates/java",
    "fileName": "ALLInstanceVars.tpl",
    "description": "Create the instance vars for a bean. Use field modifiers like final. ",
    "expose": "WEB",
    "cached": "true"
  },
  "ALLSetter.tpl": {
    "module": "builder",
    "moduleScope": "main",
    "hostKey": "localhost",
    "filePath": "templates/java",
    "fileName": "ALLSetter.tpl",
    "description": "Creates setter/getter together with a description in beans. Use field modifiers like final or override. ",
    "expose": "WEB",
    "cached": "true"
  },
  "ALLStaticNames.tpl": {
    "module": "builder",
    "moduleScope": "main",
    "hostKey": "localhost",
    "filePath": "templates/java",
    "fileName": "ALLStaticNames.tpl",
    "description": "Creates static field names for external access.  ",
    "expose": "WEB",
    "cached": "true"
  },
  "BEANCreate.tpl": {
    "module": "builder",
    "moduleScope": "main",
    "hostKey": "localhost",
    "filePath": "templates/java/bean",
    "fileName": "BEANCreate.tpl",
    "description": "Java template for beans. ",
    "expose": "WEB",
    "cached": "true"
  },
  "CALL_BEANCreate.tpl": {
    "module": "builder",
    "moduleScope": "main",
    "hostKey": "localhost",
    "filePath": "templates/java/bean",
    "fileName": "BEANCreate.tpl",
    "description": "Used for BEANCreate.tpl for generation CALL_BEAN shape.",
    "expose": "WEB",
    "cached": "false"
  },
  "CONFIGConstructor.tpl": {
    "module": "builder",
    "moduleScope": "main",
    "hostKey": "localhost",
    "filePath": "templates/java/config",
    "fileName": "CONFIGConstructor.tpl",
    "description": "Creates a constructor using a map as input for ConfigCreate template.",
    "expose": "WEB",
    "cached": "true"
  },
  "CONFIGCreate.tpl": {
    "module": "builder",
    "moduleScope": "main",
    "hostKey": "localhost",
    "filePath": "templates/java/config",
    "fileName": "CONFIGCreate.tpl",
    "description": "Java template for config classes. Creates also a constructor using a map as input.",
    "expose": "WEB",
    "cached": "true"
  },
  "data.xlsx": {
    "configModelKey": "XlsxConfig",
    "module": "builder",
    "moduleScope": "main",
    "hostKey": "localhost",
    "filePath": "classpath",
    "fileName": "data.xlsx",
    "description": "The sheet with models/fields cache definition for data definitions.",
    "expose": "WEB",
    "cached": "false",
    "properties": {
      "rowHead": 0
    }
  },
  "eo.xlsx:DbSqlConfig": {
    "configModelKey": "XlsxConfig",
    "module": "builder",
    "moduleScope": "main",
    "hostKey": "localhost",
    "filePath": ".",
    "fileName": "eo.xlsx",
    "description": "Json configurations for DbSqlConfig.",
    "expose": "WEB",
    "cached": "false",
    "properties": {
      "rowHead": 0,
      "sheetName": "DbSqlConfig"
    }
  },
  "eo.xlsx:FieldConfig": {
    "configModelKey": "XlsxConfig",
    "module": "builder",
    "moduleScope": "main",
    "hostKey": "localhost",
    "filePath": ".",
    "fileName": "eo.xlsx",
    "description": "Json configurations for FieldConfig.",
    "expose": "WEB",
    "cached": "false",
    "properties": {
      "rowHead": 0,
      "sheetName": "FieldConfig"
    }
  },
  "eo.xlsx:FileConfig": {
    "configModelKey": "XlsxConfig",
    "module": "builder",
    "moduleScope": "main",
    "hostKey": "localhost",
    "filePath": ".",
    "fileName": "eo.xlsx",
    "description": "Json configurations for FileConfig.",
    "expose": "WEB",
    "cached": "false",
    "properties": {
      "rowHead": 0,
      "sheetName": "FileConfig"
    }
  },
  "eo.xlsx:HostConfig": {
    "configModelKey": "XlsxConfig",
    "module": "builder",
    "moduleScope": "main",
    "hostKey": "localhost",
    "filePath": ".",
    "fileName": "eo.xlsx",
    "description": "Json configurations for HostConfig.",
    "expose": "WEB",
    "cached": "false",
    "properties": {
      "rowHead": 0,
      "sheetName": "HostConfig"
    }
  },
  "eo.xlsx:ModelConfig": {
    "configModelKey": "XlsxConfig",
    "module": "builder",
    "moduleScope": "main",
    "hostKey": "localhost",
    "filePath": ".",
    "fileName": "eo.xlsx",
    "description": "Json configurations for  ModelConfig.",
    "expose": "WEB",
    "cached": "false",
    "properties": {
      "rowHead": 0,
      "sheetName": "ModelConfig"
    }
  },
  "Hibernate.xml.tpl": {
    "module": "builder",
    "moduleScope": "main",
    "hostKey": "localhost",
    "filePath": "templates/xml",
    "fileName": "Hibernate.xml.tpl",
    "description": "Hibernate template",
    "expose": "WEB",
    "cached": "false"
  },
  "INTERFACECreate.tpl": {
    "module": "builder",
    "moduleScope": "main",
    "hostKey": "localhost",
    "filePath": "templates/java/interface",
    "fileName": "INTERFACECreate.tpl",
    "expose": "WEB",
    "cached": "false"
  },
  "INTERFACESetter.tpl": {
    "module": "builder",
    "moduleScope": "main",
    "hostKey": "localhost",
    "filePath": "templates/java/interface",
    "fileName": "INTERFACESetter.tpl",
    "description": "Creates getter together with a description in interfaces in cache types.  ",
    "expose": "WEB",
    "cached": "false"
  },
  "INTERFACEStaticNames.tpl": {
    "module": "builder",
    "moduleScope": "main",
    "hostKey": "localhost",
    "filePath": "templates/java/interface",
    "fileName": "INTERFACEStaticNames.tpl",
    "description": "Creates static names for interface getter.",
    "expose": "WEB",
    "cached": "false"
  },
  "JavaBuilder.tpl": {
    "module": "builder",
    "moduleScope": "main",
    "hostKey": "localhost",
    "filePath": "templates/java",
    "fileName": "JavaBuilder.tpl",
    "description": "Control directive to load ModelConfig and FieldConfig data and call GenerateJavaCall",
    "expose": "WEB",
    "cached": "false",
    "rolePermissions": {
      "execute": "superadmin"
    }
  },
  "JsonBuilder.tpl": {
    "module": "builder",
    "moduleScope": "main",
    "hostKey": "localhost",
    "filePath": "templates/json",
    "fileName": "JsonBuilder.tpl",
    "description": "Control directives to load a configuration sheet defined by configType in a hierarchical way and  call GenerateJsonCall.",
    "expose": "WEB",
    "cached": "false",
    "rolePermissions": {
      "execute": "superadmin"
    }
  }
}