{
  "XlsxConfig": {
    "module": "eo-xlsx",
    "moduleScope": "main",
    "fieldKeys": [
      "sheetName"
    ],
    "superKey": "FileConfig",
    "expose": "NONE",
    "description": "The cache class for excel access. Contains the file cache.",
    "packagePath": "org.fluentcodes.projects.elasticobjects.calls.xlsx",
    "modelKey": "XlsxConfig",
    "properties": {
      "classPath": "src.main.java",
      "create": false,
      "shapeType": "CONFIG"
    },
    "author": "Werner Diwischek"
  },
  "XlsxReadCall": {
    "module": "eo-xlsx",
    "moduleScope": "main",
    "interfaces": "ListInterface",
    "superKey": "FileReadCall",
    "expose": "WEB",
    "description": "Executes a call  for the file and sheet defined in XlsxConfig configuration.",
    "packagePath": "org.fluentcodes.projects.elasticobjects.calls.xlsx",
    "modelKey": "XlsxReadCall",
    "properties": {
      "classPath": "src.main.java",
      "create": true,
      "shapeType": "CALL_BEAN"
    },
    "author": "Werner Diwischek"
  }
}